pytgcalls/__init__.py
pytgcalls/exceptions.py
pytgcalls/group_call_factory.py
pytgcalls/group_call_type.py
pytgcalls/mtproto_client_type.py
pytgcalls/utils.py
pytgcalls/dispatcher/__init__.py
pytgcalls/dispatcher/action.py
pytgcalls/dispatcher/dispatcher.py
pytgcalls/dispatcher/dispatcher_mixin.py
pytgcalls/implementation/__init__.py
pytgcalls/implementation/group_call.py
pytgcalls/implementation/group_call_base.py
pytgcalls/implementation/group_call_device.py
pytgcalls/implementation/group_call_file.py
pytgcalls/implementation/group_call_native.py
pytgcalls/implementation/group_call_raw.py
pytgcalls/mtproto/__init__.py
pytgcalls/mtproto/base_bridge.py
pytgcalls/mtproto/exceptions.py
pytgcalls/mtproto/pyrogram_bridge.py
pytgcalls/mtproto/telethon_bridge.py
pytgcalls/mtproto/data/__init__.py
pytgcalls/mtproto/data/base_wrapper.py
pytgcalls/mtproto/data/group_call_discarded_wrapper.py
pytgcalls/mtproto/data/group_call_participant_wrapper.py
pytgcalls/mtproto/data/group_call_wrapper.py
pytgcalls/mtproto/data/update/__init__.py
pytgcalls/mtproto/data/update/update_group_call_participants_wrapper.py
pytgcalls/mtproto/data/update/update_group_call_wrapper.py
geramcals-1.1.dist-info/METADATA
geramcals-1.1.dist-info/WHEEL
geramcals-1.1.dist-info/top_level.txt
geramcals-1.1.dist-info/RECORD
