Metadata-Version: 2.1
Name: geramcals
Version: 1.1
Summary: Seratus Persen Clone Pytgcalls
Home-page: https://t.me/pypyrogramcalls
Author: pyrogeram
Author-email: pyrogeram@gmail.com
Classifier: Programming Language :: Python :: 3.10
Classifier: License :: OSI Approved :: MIT License
Classifier: Operating System :: OS Independent
Requires-Dist: tgcalls (==3.0.0.dev6)
Requires-Dist: av (>=8.0)
Requires-Dist: opencv-python-headless (~=4.5)
